shapes_geometry/__init__.py
shapes_geometry/__main__.py
shapes_geometry/exceptions.py
shapes_geometry/utils.py
shapes_geometry/shapes/__init__.py
shapes_geometry/shapes/capsule.py
shapes_geometry/shapes/circle.py
shapes_geometry/shapes/cone.py
shapes_geometry/shapes/cube.py
shapes_geometry/shapes/cuboid.py
shapes_geometry/shapes/cylinder.py
shapes_geometry/shapes/decagon.py
shapes_geometry/shapes/hexagon.py
shapes_geometry/shapes/kite.py
shapes_geometry/shapes/octagon.py
shapes_geometry/shapes/parallelogram.py
shapes_geometry/shapes/pentagon.py
shapes_geometry/shapes/rectangle.py
shapes_geometry/shapes/rhombus.py
shapes_geometry/shapes/semicircle.py
shapes_geometry/shapes/sphere.py
shapes_geometry/shapes/square.py
shapes_geometry/shapes/trapezium.py
shapes_geometry/shapes/triangle.py
shapes_geometry-0.1.5.dist-info/LICENSE.txt
shapes_geometry-0.1.5.dist-info/METADATA
shapes_geometry-0.1.5.dist-info/WHEEL
shapes_geometry-0.1.5.dist-info/top_level.txt
shapes_geometry-0.1.5.dist-info/RECORD
