Metadata-Version: 2.1
Name: shapes-geometry
Version: 0.1.5
Summary: Functions to calculate geometric properties of 2D and 3D shapes.
Home-page: https://github.com/Arunk292002/shapes-geometry
Author: Arunkumar
Author-email: arun5412ten@gmail.com
Keywords: geometry shapes math area volume 2D 3D
Classifier: Programming Language :: Python :: 3
Classifier: License :: OSI Approved :: MIT License
Classifier: Operating System :: OS Independent
Classifier: Intended Audience :: Education
Requires-Python: >=3.6
License-File: LICENSE.txt
